.gitignore
.travis.yml
LICENSE
LICENSE_of_Cellpose
MANIFEST.in
README.md
environment.yml
imagej_roi_converter.py
logo.svg
setup.cfg
setup.py
scellseg/__init__.py
scellseg/__main__.py
scellseg/core.py
scellseg/dataset.py
scellseg/dynamics.py
scellseg/io.py
scellseg/metrics.py
scellseg/models.py
scellseg/net_desc.py
scellseg/net_utils.py
scellseg/plot.py
scellseg/transforms.py
scellseg/utils.py
scellseg.egg-info/PKG-INFO
scellseg.egg-info/SOURCES.txt
scellseg.egg-info/dependency_links.txt
scellseg.egg-info/entry_points.txt
scellseg.egg-info/requires.txt
scellseg.egg-info/top_level.txt
scellseg/assets/contrast_data/Kc167/095_img.png
scellseg/assets/contrast_data/Kc167/095_masks.png
scellseg/assets/contrast_data/Kc167/096_img.png
scellseg/assets/contrast_data/Kc167/096_masks.png
scellseg/assets/contrast_data/Kc167/097_img.png
scellseg/assets/contrast_data/Kc167/097_masks.png
scellseg/assets/contrast_data/Kc167/102_img.png
scellseg/assets/contrast_data/Kc167/102_masks.png
scellseg/assets/contrast_data/Kc167/103_img.png
scellseg/assets/contrast_data/Kc167/103_masks.png
scellseg/assets/contrast_data/cytomembrane/290_img.png
scellseg/assets/contrast_data/cytomembrane/290_masks.png
scellseg/assets/contrast_data/cytomembrane/306_img.png
scellseg/assets/contrast_data/cytomembrane/306_masks.png
scellseg/assets/contrast_data/cytomembrane/309_img.png
scellseg/assets/contrast_data/cytomembrane/309_masks.png
scellseg/assets/contrast_data/cytomembrane/311_img.png
scellseg/assets/contrast_data/cytomembrane/311_masks.png
scellseg/assets/contrast_data/cytomembrane/326_img.png
scellseg/assets/contrast_data/cytomembrane/326_masks.png
scellseg/assets/contrast_data/macrophagocyte/104_img.png
scellseg/assets/contrast_data/macrophagocyte/104_masks.png
scellseg/assets/contrast_data/macrophagocyte/106_img.png
scellseg/assets/contrast_data/macrophagocyte/106_masks.png
scellseg/assets/contrast_data/macrophagocyte/107_img.png
scellseg/assets/contrast_data/macrophagocyte/107_masks.png
scellseg/assets/contrast_data/macrophagocyte/110_img.png
scellseg/assets/contrast_data/macrophagocyte/110_masks.png
scellseg/assets/contrast_data/macrophagocyte/121_img.png
