Metadata-Version: 2.1
Name: scellseg
Version: 0.1.8
Summary: a specializable cell segmentation tool
Home-page: https://github.com/cellimnet/scellseg-publish
Author: Dejin Xun & Deheng Chen
Author-email: xundejin@zju.edu.cn
License: BSD
Platform: UNKNOWN
Classifier: Programming Language :: Python :: 3
Classifier: License :: OSI Approved :: BSD License
Classifier: Operating System :: OS Independent
License-File: LICENSE
License-File: LICENSE_of_Cellpose
